{
    "$schema": "http://json-schema.org/schema#",
    "type": "object",
    "properties": {
        "extraLogProcessingStages": {
            "type": "string"
        },
        "jobLabel": {
            "type": "string"
        },
        "labelSelectors": {
            "type": "object",
            "properties": {
                "app.kubernetes.io/name": {
                    "type": "string"
                }
            }
        },
        "structuredMetadata": {
            "type": "object"
        }
    }
}
